{"id":"4532291","lastModifiedDate":"2024-06-14T12:31:03Z","publishedAbstract":"`MountVolume.WaitForAttach` failed for volume with \u0026quot;structure needs cleaning\u0026quot; ~~~ 2:02:45 PM Warning Failed Mount MountVolume.WaitForAttach failed for volume \u0026quot;pvc-62c6563e-8cac-11e9-bba9-005056b0bf31\u0026quot;: Heuristic determination of mount point failed:stat /var/lib/origin/openshift.local.volumes/plugins/kubernetes.io/iscsi/iface-default/XX.XX.XX.XX:3260-iqn.2016-12.org.gluster-block:3eeb31cf-3289-4052-a690-5831f6aac34a-lun-0: Structure needs cleaning ~~~","publishedTitle":"MountVolume.WaitForAttach failed for volume with \"structure needs cleaning\"","setLanguage":"en","view_uri":"https://access.redhat.com/solutions/4532291"}