{"id":"4776841","lastModifiedDate":"2024-06-14T02:15:55Z","publishedAbstract":"* noobaa-operator pod is stuck in Initializing state when deploying OCS 4 in a proxy enabled environment. * noobaa-operator pod returns `status code: 403` error while creating the default noobaa backing store in a UPI VMware environment ~~~ time=\u0026quot;2020-01-23T09:46:38Z\u0026quot; level=info msg=\u0026quot;creating bucket noobaa-backing-store-ed24f6c7-579c-49da-a8ed-b07a299a6b8e\u0026quot; sys=openshift-storage/noobaa time=\u0026quot;2020-01-23T09:23:36Z\u0026quot; level=error msg=\u0026quot;got error when trying to create bucket noobaa-backing-store-62e0c28e-b598-413a-86e6-ee56bbf8141b. error: SerializationError: failed to unmarshal error message\\n\\tstatus code: 403, request id:, host id: \\ncaused by: Unmarshal Error: failed to unmarshal error message\\n\\t00000000 ~~~ ","publishedTitle":"Noobaa-operator pod is stuck in init state when deploying OCS 4 in a proxy  environment.","setLanguage":"en","view_uri":"https://access.redhat.com/solutions/4776841"}