{"id":"4862821","lastModifiedDate":"2024-06-14T02:05:18Z","publishedAbstract":"* \u0026#039;noobaa-operator\u0026#039; is stuck while creating an OBC using \u0026#039;lib-bucket-provisioner\u0026#039; in OCS 4.2 cluster, with the following error: \u0026quot;E0227 16:55:55.508374 1 controller.go:190] error syncing \u0026#039;openshift-storage/migstorage\u0026#039;: error updating OBC status:%!(EXTRA *errors.StatusError=ObjectBucketClaim.objectbucket.io \u0026quot;migstorage\u0026quot; is invalid: status.phase: Unsupported value: \u0026quot;Pending\u0026quot;: supported values: \u0026quot;pending\u0026quot;, \u0026quot;bound\u0026quot;, \u0026quot;released\u0026quot;, \u0026quot;failed\u0026quot;), requeuing\u0026quot; ","publishedTitle":"'noobaa-operator' is stuck while creating an OBC using 'lib-bucket-provisioner' in OCS 4.2 cluster.","setLanguage":"en","view_uri":"https://access.redhat.com/solutions/4862821"}